flaightkit-0.4.0.data/scripts/entrypoint.py
flaightkit-0.4.0.data/scripts/flytekit_build_image.sh
flaightkit-0.4.0.data/scripts/flytekit_sagemaker_runner.py
flaightkit-0.4.0.data/scripts/flytekit_venv
flytekit/__init__.py
flytekit/loggers.py
flytekit/bin/__init__.py
flytekit/bin/entrypoint.py
flytekit/clients/__init__.py
flytekit/clients/friendly.py
flytekit/clients/helpers.py
flytekit/clients/raw.py
flytekit/clis/__init__.py
flytekit/clis/helpers.py
flytekit/clis/auth/__init__.py
flytekit/clis/auth/auth.py
flytekit/clis/auth/credentials.py
flytekit/clis/auth/discovery.py
flytekit/clis/flyte_cli/__init__.py
flytekit/clis/flyte_cli/main.py
flytekit/clis/sdk_in_container/__init__.py
flytekit/clis/sdk_in_container/basic_auth.py
flytekit/clis/sdk_in_container/constants.py
flytekit/clis/sdk_in_container/fast_register.py
flytekit/clis/sdk_in_container/launch_plan.py
flytekit/clis/sdk_in_container/local_cache.py
flytekit/clis/sdk_in_container/package.py
flytekit/clis/sdk_in_container/placeholders.py
flytekit/clis/sdk_in_container/pyflyte.py
flytekit/clis/sdk_in_container/register.py
flytekit/clis/sdk_in_container/serialize.py
flytekit/common/__init__.py
flytekit/common/component_nodes.py
flytekit/common/constants.py
flytekit/common/interface.py
flytekit/common/launch_plan.py
flytekit/common/local_workflow.py
flytekit/common/nodes.py
flytekit/common/notifications.py
flytekit/common/promise.py
flytekit/common/schedules.py
flytekit/common/sdk_bases.py
flytekit/common/translator.py
flytekit/common/utils.py
flytekit/common/workflow.py
flytekit/common/workflow_execution.py
flytekit/common/core/__init__.py
flytekit/common/core/identifier.py
flytekit/common/exceptions/__init__.py
flytekit/common/exceptions/base.py
flytekit/common/exceptions/scopes.py
flytekit/common/exceptions/system.py
flytekit/common/exceptions/user.py
flytekit/common/mixins/__init__.py
flytekit/common/mixins/artifact.py
flytekit/common/mixins/hash.py
flytekit/common/mixins/launchable.py
flaightkit-0.4.0.dist-info/LICENSE
flaightkit-0.4.0.dist-info/METADATA
flaightkit-0.4.0.dist-info/WHEEL
flaightkit-0.4.0.dist-info/entry_points.txt
flaightkit-0.4.0.dist-info/top_level.txt
flaightkit-0.4.0.dist-info/RECORD
