Metadata-Version: 2.1
Name: flaightkit
Version: 0.4.0
Summary: Flyte SDK for Python (Latch fork)
Home-page: 
Maintainer: maximsmol
Maintainer-email: max@latch.bio
License: apache2
Platform: UNKNOWN
Classifier: Intended Audience :: Science/Research
Classifier: Intended Audience :: Developers
Classifier: License :: OSI Approved :: Apache Software License
Classifier: Programming Language :: Python :: 3.7
Classifier: Programming Language :: Python :: 3.8
Classifier: Topic :: Scientific/Engineering
Classifier: Topic :: Scientific/Engineering :: Artificial Intelligence
Classifier: Topic :: Software Development
Classifier: Topic :: Software Development :: Libraries
Classifier: Topic :: Software Development :: Libraries :: Python Modules
Requires-Python: >=3.6
License-File: LICENSE
Requires-Dist: flaightidl (==0.1.1)
Requires-Dist: wheel (<1.0.0,>=0.30.0)
Requires-Dist: pandas (<1.4.0,>=1.0.0)
Requires-Dist: click (<8.0,>=6.6)
Requires-Dist: croniter (<4.0.0,>=0.3.20)
Requires-Dist: deprecated (<2.0,>=1.0)
Requires-Dist: python-dateutil (<=2.8.1,>=2.1)
Requires-Dist: grpcio (<2.0,>=1.3.0)
Requires-Dist: protobuf (<4,>=3.6.1)
Requires-Dist: python-json-logger (>=2.0.0)
Requires-Dist: pytimeparse (<2.0.0,>=1.1.8)
Requires-Dist: pytz (<2018.5,>=2017.2)
Requires-Dist: keyring (>=18.0.1)
Requires-Dist: requests (<3.0.0,>=2.18.4)
Requires-Dist: responses (>=0.10.7)
Requires-Dist: six (<2.0.0,>=1.9.0)
Requires-Dist: sortedcontainers (<3.0.0,>=1.5.9)
Requires-Dist: statsd (<4.0.0,>=3.0.0)
Requires-Dist: urllib3 (<2.0.0,>=1.22)
Requires-Dist: wrapt (<2.0.0,>=1.0.0)
Requires-Dist: retry (==0.9.2)
Requires-Dist: dataclasses-json (>=0.5.2)
Requires-Dist: marshmallow-jsonschema (>=0.12.0)
Requires-Dist: natsort (>=7.0.1)
Requires-Dist: dirhash (>=0.2.1)
Requires-Dist: docker-image-py (>=0.1.10)
Requires-Dist: docstring-parser (>=0.9.0)
Requires-Dist: joblib (>=1.0.0)
Requires-Dist: pyyaml (==5.4.1)
Requires-Dist: singledispatchmethod ; python_version < "3.8.0"
Provides-Extra: all
Requires-Dist: pyspark (>=3.0.0) ; extra == 'all'
Requires-Dist: k8s-proto (<1.0.0,>=0.0.3) ; extra == 'all'
Requires-Dist: numpy (<2.0.0,>=1.14.0) ; extra == 'all'
Requires-Dist: pandas (<2.0.0,>=0.22.0) ; extra == 'all'
Requires-Dist: hmsclient (<1.0.0,>=0.0.1) ; extra == 'all'
Requires-Dist: papermill (>=1.2.0) ; extra == 'all'
Requires-Dist: nbconvert (>=6.0.7) ; extra == 'all'
Requires-Dist: ipykernel (<6.0.0,>=5.0.0) ; extra == 'all'
Requires-Dist: sagemaker-training (<4.0.0,>=3.6.2) ; extra == 'all'
Provides-Extra: all-spark2.4
Requires-Dist: pyspark (<3.0.0,>=2.4.0) ; extra == 'all-spark2.4'
Requires-Dist: k8s-proto (<1.0.0,>=0.0.3) ; extra == 'all-spark2.4'
Requires-Dist: numpy (<2.0.0,>=1.14.0) ; extra == 'all-spark2.4'
Requires-Dist: pandas (<2.0.0,>=0.22.0) ; extra == 'all-spark2.4'
Requires-Dist: hmsclient (<1.0.0,>=0.0.1) ; extra == 'all-spark2.4'
Requires-Dist: papermill (>=1.2.0) ; extra == 'all-spark2.4'
Requires-Dist: nbconvert (>=6.0.7) ; extra == 'all-spark2.4'
Requires-Dist: ipykernel (<6.0.0,>=5.0.0) ; extra == 'all-spark2.4'
Requires-Dist: sagemaker-training (<4.0.0,>=3.6.2) ; extra == 'all-spark2.4'
Provides-Extra: hive_sensor
Requires-Dist: hmsclient (<1.0.0,>=0.0.1) ; extra == 'hive_sensor'
Provides-Extra: notebook
Requires-Dist: papermill (>=1.2.0) ; extra == 'notebook'
Requires-Dist: nbconvert (>=6.0.7) ; extra == 'notebook'
Requires-Dist: ipykernel (<6.0.0,>=5.0.0) ; extra == 'notebook'
Provides-Extra: sagemaker
Requires-Dist: sagemaker-training (<4.0.0,>=3.6.2) ; extra == 'sagemaker'
Provides-Extra: schema
Requires-Dist: numpy (<2.0.0,>=1.14.0) ; extra == 'schema'
Requires-Dist: pandas (<2.0.0,>=0.22.0) ; extra == 'schema'
Provides-Extra: sidecar
Requires-Dist: k8s-proto (<1.0.0,>=0.0.3) ; extra == 'sidecar'
Provides-Extra: spark
Requires-Dist: pyspark (<3.0.0,>=2.4.0) ; extra == 'spark'
Provides-Extra: spark3
Requires-Dist: pyspark (>=3.0.0) ; extra == 'spark3'
